[
    {
        "user_uid": 1292808363,
        "created_at": [
            2018,
            5,
            15
        ],
        "scheme": "https://m.weibo.cn/status/GgJtn65I6?mblogid=GgJtn65I6&luicode=10000011&lfid=1076031292808363",
        "text": "【黄瓜炒香蕉了解一下？高校食堂推出减肥餐，卖4块钱一份】5月14日，<a href='https://m.weibo.cn/n/河南工程学院'>@河南工程学院</a> 食堂推出减肥套餐：黄瓜炒香蕉、西红柿炒菠萝，食堂大叔说如果卖得好还会推出新品。网友：颜色看着不错，不知道味道如何？<span class=\"url-icon\"><img src=\"//h5.sinaimg.cn/m/emoticon/icon/default/d_yunbei-c6964bf237.png\" style=\"width:1em;height:1em;\" alt=\"[允悲]\"></span> <a data-url=\"http://t.cn/R3iqGfW\" href=\"http://miaopai.com/show/VihM6szh1LHID9WCOVvUrnP-r9dergoxO60JqQ__.htm?from=1110006030&weiboauthoruid=1292808363&showurl=http%3A%2F%2Fmiaopai.com%2Fshow%2FVihM6szh1LHID9WCOVvUrnP-r9dergoxO60JqQ__.htm%3Ffrom%3D1110006030%26weiboauthoruid%3D1292808363&url_open_direct=1&toolbar_hidden=1&url_type=39&object_type=video&pos=1&containerid=2304423ced8d18534977cd3348e94982183632&luicode=10000011&lfid=1076031292808363&ep=GgJtn65I6%252C1292808363%252CGgJtn65I6%252C1292808363\" data-hide=\"\"><span class=\"url-icon\"><img src=\"https://h5.sinaimg.cn/upload/2015/09/25/3/timeline_card_small_video_default.png\"></span></i><span class=\"surl-text\">一手video的秒拍视频</a> ​​​",
        "pics": [],
        "comments_count": 10,
        "attitudes_count": 14,
        "reposts_count": 9
    },
    {
        "user_uid": 1292808363,
        "created_at": [
            2018,
            5,
            15
        ],
        "scheme": "https://m.weibo.cn/status/GgJ5smREm?mblogid=GgJ5smREm&luicode=10000011&lfid=1076031292808363",
        "text": "弹头作词的周杰伦最新单曲《不爱我就拉倒》歌词中居然出现了哥练的胸肌？这叫女生怎么唱啊<span class=\"url-icon\"><img src=\"//h5.sinaimg.cn/m/emoticon/icon/default/d_feijie-c1d5b12e04.png\" style=\"width:1em;height:1em;\" alt=\"[费解]\"></span>随后方文山微博评论区沦陷，网友疯狂喊话方文山回来上班！被评论笑死<span class=\"url-icon\"><img src=\"//h5.sinaimg.cn/m/emoticon/icon/default/d_yunbei-c6964bf237.png\" style=\"width:1em;height:1em;\" alt=\"[允悲]\"></span> ​​​",
        "pics": [
            "https://wx4.sinaimg.cn/large/4d0eb0ably1frbqy5bw56j20c80lqt9a.jpg",
            "https://wx4.sinaimg.cn/large/4d0eb0ably1frbqy5ndyvj20c80lrq44.jpg",
            "https://wx2.sinaimg.cn/large/4d0eb0ably1frbqy61zjaj20c80lrmyf.jpg",
            "https://wx3.sinaimg.cn/large/4d0eb0ably1frbqy68thpj20c80lrwfo.jpg",
            "https://wx1.sinaimg.cn/large/4d0eb0ably1frbqy6flz7j20c80lrgmw.jpg",
            "https://wx2.sinaimg.cn/large/4d0eb0ably1frbqy718tnj20c80lr0tv.jpg",
            "https://wx2.sinaimg.cn/large/4d0eb0ably1frbqy78di7j20c80lrjsj.jpg",
            "https://wx4.sinaimg.cn/large/4d0eb0ably1frbqy7hlexj20c80lrgms.jpg",
            "https://wx3.sinaimg.cn/large/4d0eb0ably1frbqy524cmj20c80lr3zp.jpg"
        ],
        "comments_count": 68,
        "attitudes_count": 200,
        "reposts_count": 64
    }
]